marcxml2mods
