Metadata-Version: 1.1
Name: marcxml2mods
Version: 0.2.5
Summary: Conversion from MARCXML/OAI to MODS, which is used in NK CZ.
Home-page: https://github.com/edeposit/marcxml2mods
Author: Edeposit team
Author-email: edeposit@email.cz
License: MIT
Platform: UNKNOWN
Classifier: Development Status :: 4 - Beta
Classifier: Intended Audience :: Developers
Classifier: License :: OSI Approved :: MIT License
Classifier: Programming Language :: Python :: 2
Classifier: Programming Language :: Python :: 2.7
Classifier: Topic :: Text Processing :: Markup :: XML
Classifier: Topic :: Software Development :: Libraries :: Python Modules
